fast_error_saver/__init__.py
fast_error_saver/error_saver.py
fast_error_saver/utils/__init__.py
fast_error_saver/utils/type_saver.py
tests/__init__.py
fast_error_saver-0.2.0.dist-info/METADATA
fast_error_saver-0.2.0.dist-info/WHEEL
fast_error_saver-0.2.0.dist-info/top_level.txt
fast_error_saver-0.2.0.dist-info/RECORD
