Metadata-Version: 2.1
Name: fast_error_saver
Version: 0.2.0
Summary: Auto save checkpoints when you code raise some exception.
Home-page: https://github.com/Yu-Jie1669/checkpointer
Author: Yj Lin
Author-email: yjlin2001@gmail.com
Classifier: Programming Language :: Python :: 3
Classifier: License :: OSI Approved :: MIT License
Classifier: Operating System :: OS Independent
Requires-Python: >=3.6
Requires-Dist: numpy
